{"type":"FeatureCollection","features":[{"type":"Feature","properties":{"name":"Port-Gentil"},"geometry":{"type":"Point","coordinates":[8.776702880859375,-0.7149510805048169]}},{"type":"Feature","properties":{"name":"Libreville"},"geometry":{"type":"Point","coordinates":[9.4482421875,0.36254640877526295]}},{"type":"Feature","properties":{"name":"Oyem"},"geometry":{"type":"Point","coordinates":[11.572723388671875,1.5969306533257908]}},{"type":"Feature","properties":{"name":"Franceville"},"geometry":{"type":"Point","coordinates":[13.58957290649414,-1.6327936314770728]}}]}